<repast.simphony.data2.engine.DataSetDescriptor simphonyVersion="2.5.0">
  <name>Education</name>
  <type>AGGREGATE</type>
  <inclTick>true</inclTick>
  <inclBatchRun>false</inclBatchRun>
  <inclRandomSeed>false</inclRandomSeed>
  <scheduleParams>
    <start>1.0</start>
    <interval>1.0</interval>
    <priority>-Infinity</priority>
    <pType>LAST</pType>
    <duration>-1.0</duration>
    <frequency>REPEAT</frequency>
    <hashCode>-47868834</hashCode>
  </scheduleParams>
  <atEnd>false</atEnd>
  <methodDataSources class="linked-hash-map"/>
  <countSources class="linked-hash-map"/>
  <customNADataSources class="linked-hash-map"/>
  <customAggDataSources class="linked-hash-map">
    <entry>
      <string>EducationLevel_0</string>
      <repast.simphony.data2.engine.CustomDataSourceDefinition>
        <id>EducationLevel_0</id>
        <dsClassName>com.qinshp.datasource.EducationLevel_0DataSource</dsClassName>
      </repast.simphony.data2.engine.CustomDataSourceDefinition>
    </entry>
    <entry>
      <string>EducationLevel_1</string>
      <repast.simphony.data2.engine.CustomDataSourceDefinition>
        <id>EducationLevel_1</id>
        <dsClassName>com.qinshp.datasource.EducationLevel_1DataSource</dsClassName>
      </repast.simphony.data2.engine.CustomDataSourceDefinition>
    </entry>
    <entry>
      <string>EducationLevel_2</string>
      <repast.simphony.data2.engine.CustomDataSourceDefinition>
        <id>EducationLevel_2</id>
        <dsClassName>com.qinshp.datasource.EducationLevel_2DataSource</dsClassName>
      </repast.simphony.data2.engine.CustomDataSourceDefinition>
    </entry>
    <entry>
      <string>EducationLevel_3</string>
      <repast.simphony.data2.engine.CustomDataSourceDefinition>
        <id>EducationLevel_3</id>
        <dsClassName>com.qinshp.datasource.EducationLevel_3DataSource</dsClassName>
      </repast.simphony.data2.engine.CustomDataSourceDefinition>
    </entry>
    <entry>
      <string>EducationLevel_4</string>
      <repast.simphony.data2.engine.CustomDataSourceDefinition>
        <id>EducationLevel_4</id>
        <dsClassName>com.qinshp.datasource.EducationLevel_4DataSource</dsClassName>
      </repast.simphony.data2.engine.CustomDataSourceDefinition>
    </entry>
    <entry>
      <string>EducationLevel_5</string>
      <repast.simphony.data2.engine.CustomDataSourceDefinition>
        <id>EducationLevel_5</id>
        <dsClassName>com.qinshp.datasource.EducationLevel_5DataSource</dsClassName>
      </repast.simphony.data2.engine.CustomDataSourceDefinition>
    </entry>
    <entry>
      <string>EducationLevel_6</string>
      <repast.simphony.data2.engine.CustomDataSourceDefinition>
        <id>EducationLevel_6</id>
        <dsClassName>com.qinshp.datasource.EducationLevel_6DataSource</dsClassName>
      </repast.simphony.data2.engine.CustomDataSourceDefinition>
    </entry>
    <entry>
      <string>EducationLevel_7</string>
      <repast.simphony.data2.engine.CustomDataSourceDefinition>
        <id>EducationLevel_7</id>
        <dsClassName>com.qinshp.datasource.EducationLevel_7DataSource</dsClassName>
      </repast.simphony.data2.engine.CustomDataSourceDefinition>
    </entry>
    <entry>
      <string>EducationLevel_8</string>
      <repast.simphony.data2.engine.CustomDataSourceDefinition>
        <id>EducationLevel_8</id>
        <dsClassName>com.qinshp.datasource.EducationLevel_8DataSource</dsClassName>
      </repast.simphony.data2.engine.CustomDataSourceDefinition>
    </entry>
    <entry>
      <string>EducationLevel_9</string>
      <repast.simphony.data2.engine.CustomDataSourceDefinition>
        <id>EducationLevel_9</id>
        <dsClassName>com.qinshp.datasource.EducationLevel_9DataSource</dsClassName>
      </repast.simphony.data2.engine.CustomDataSourceDefinition>
    </entry>
  </customAggDataSources>
</repast.simphony.data2.engine.DataSetDescriptor>